steel/__init__.py
steel/_base_client.py
steel/_client.py
steel/_compat.py
steel/_constants.py
steel/_exceptions.py
steel/_files.py
steel/_models.py
steel/_qs.py
steel/_resource.py
steel/_response.py
steel/_streaming.py
steel/_types.py
steel/_version.py
steel/pagination.py
steel/py.typed
steel/_utils/__init__.py
steel/_utils/_compat.py
steel/_utils/_datetime_parse.py
steel/_utils/_logs.py
steel/_utils/_proxy.py
steel/_utils/_reflection.py
steel/_utils/_resources_proxy.py
steel/_utils/_streams.py
steel/_utils/_sync.py
steel/_utils/_transform.py
steel/_utils/_typing.py
steel/_utils/_utils.py
steel/lib/.keep
steel/resources/__init__.py
steel/resources/credentials.py
steel/resources/extensions.py
steel/resources/files.py
steel/resources/profiles.py
steel/resources/sessions/__init__.py
steel/resources/sessions/captchas.py
steel/resources/sessions/files.py
steel/resources/sessions/sessions.py
steel/types/__init__.py
steel/types/client_pdf_params.py
steel/types/client_scrape_params.py
steel/types/client_screenshot_params.py
steel/types/credential_create_params.py
steel/types/credential_create_response.py
steel/types/credential_delete_params.py
steel/types/credential_delete_response.py
steel/types/credential_list_params.py
steel/types/credential_list_response.py
steel/types/credential_update_params.py
steel/types/credential_update_response.py
steel/types/extension_delete_all_response.py
steel/types/extension_delete_response.py
steel/types/extension_download_response.py
steel/types/extension_list_response.py
steel/types/extension_update_params.py
steel/types/extension_update_response.py
steel/types/extension_upload_params.py
steel/types/extension_upload_response.py
steel/types/file.py
steel/types/file_upload_params.py
steel/types/fileslist.py
steel/types/pdf_response.py
steel/types/profile_create_params.py
steel/types/profile_create_response.py
steel/types/profile_list_response.py
steel/types/scrape_response.py
steel/types/screenshot_response.py
steel/types/session.py
steel_sdk-0.15.0.dist-info/METADATA
steel_sdk-0.15.0.dist-info/WHEEL
steel_sdk-0.15.0.dist-info/licenses/LICENSE
steel_sdk-0.15.0.dist-info/RECORD
